outline/__init__.py
outline/client.py
outline/exceptions.py
outline/models/__init__.py
outline/models/attachment.py
outline/models/base.py
outline/models/collection.py
outline/models/comment.py
outline/models/document.py
outline_kb_sdk-0.9.0.dist-info/METADATA
outline_kb_sdk-0.9.0.dist-info/WHEEL
outline_kb_sdk-0.9.0.dist-info/licenses/LICENSE
outline_kb_sdk-0.9.0.dist-info/RECORD
